{"details":[{"details":[{"details":[{"fields":{"published":"2018-01-07T20:41:33Z","referrer.host":[{"key":"toppuppies.co.uk","value":2166},{"key":"news.ing.example.com","value":38},{"key":"apple.com","value":24},{"key":"www.my-daily-news-site-times.com","value":12},{"key":"examplekittens.com","value":8}],"segment":{"path":"","slug":""},"title":"Social Media Waits To See How She Weathers Storm"},"key":4722568,"metrics":{"bounce-rate":84.72,"hits":1441,"sessions":1067}},{"fields":{"published":"2018-01-07T05:12:10Z","referrer.host":[{"key":"examplekittens.com","value":106},{"key":"toppuppies.co.uk","value":21},{"key":"placekitten.com","value":4},{"key":"a.example.com","value":4},{"key":"www.topbuzz.com","value":4}],"segment":{"path":"","slug":""},"title":"Meghan Markle Something or Another"},"key":4722180,"metrics":{"bounce-rate":75,"hits":107,"sessions":72}},{"fields":{"published":"2018-01-07T00:58:23Z","referrer.host":[{"key":"examplekittens.com","value":197},{"key":"toppuppies.co.uk","value":72},{"key":"placekitten.com","value":18},{"key":"www.linkedin.com","value":12},{"key":"apple.com","value":7}],"segment":{"path":"","slug":""},"title":"Plane takes off and then lands again!"},"key":4722046,"metrics":{"bounce-rate":78.21,"hits":232,"sessions":179}},{"fields":{"published":"2018-01-06T23:44:47Z","referrer.host":[{"key":"toppuppies.co.uk","value":1144},{"key":"examplekittens.com","value":39},{"key":"apple.com","value":2}],"segment":{"path":"news/","slug":"news"},"title":"Trump \u0026#8216;Embarrassing\u0026#8217 pops Up On Twitter"},"key":4721713,"metrics":{"bounce-rate":89.18,"hits":640,"sessions":555}},{"fields":{"published":"2018-01-04T22:45:05Z","referrer.host":[{"key":"examplekittens.com","value":1197},{"key":"toppuppies.co.uk","value":8},{"key":"m.example.com","value":2}],"segment":{"path":"news/","slug":"news"},"title":"Something interesting and witty"},"key":4718623,"metrics":{"bounce-rate":83.43,"hits":754,"sessions":634}}],"dimensions":["article.id"],"fields":{"referrer.host":[{"key":"toppuppies.co.uk","value":3411},{"key":"examplekittens.com","value":1547},{"key":"news.ing.example.com","value":38},{"key":"apple.com","value":33},{"key":"placekitten.com","value":22},{"key":"www.my-daily-news-site-times.com","value":12},{"key":"www.linkedin.com","value":12},{"key":"www.topbuzz.com","value":4},{"key":"a.example.com","value":4},{"key":"m.example.com","value":2}]},"key":"2018-01-08T00:00:00.000Z","metrics":{"bounce-rate":84.64,"hits":3174,"sessions":2507}},{"details":[{"fields":{"published":"2018-01-07T05:12:10Z","referrer.host":[{"key":"toppuppies.co.uk","value":427},{"key":"examplekittens.com","value":227},{"key":"news.ing.example.com","value":196},{"key":"news.example.ca","value":34},{"key":"www.my-daily-news-site-times.com","value":19}],"segment":{"path":"","slug":""},"title":"Meghan Markle Something or Another"},"key":4722180,"metrics":{"bounce-rate":76.88,"hits":1010,"sessions":718}},{"fields":{"published":"2018-01-07T00:58:23Z","referrer.host":[{"key":"examplekittens.com","value":4691},{"key":"toppuppies.co.uk","value":2099},{"key":"www.my-daily-news-site-times.com","value":84},{"key":"placekitten.com","value":68},{"key":"apple.com","value":31}],"segment":{"path":"","slug":""},"title":"Plane takes off and then lands again!"},"key":4722046,"metrics":{"bounce-rate":74.92,"hits":5020,"sessions":3554}},{"fields":{"published":"2018-01-06T23:44:47Z","referrer.host":[{"key":"toppuppies.co.uk","value":17380},{"key":"examplekittens.com","value":554},{"key":"www.my-daily-news-site-times.com","value":92},{"key":"t.co","value":14},{"key":"apple.com","value":13}],"segment":{"path":"news/","slug":"news"},"title":"Trump \u0026#8216;Embarrassing\u0026#8217 pops Up On Twitter"},"key":4721713,"metrics":{"bounce-rate":89.32,"hits":10316,"sessions":8226}},{"fields":{"published":"2018-01-06T15:17:26Z","referrer.host":[{"key":"toppuppies.co.uk","value":4939},{"key":"apple.com","value":15},{"key":"www.my-daily-news-site-times.com","value":15},{"key":"examplekittens.com","value":5},{"key":"www-my-daily-news-site-times-com.cdn.ampproject.org","value":5}],"segment":{"path":"","slug":""},"title":"Icecream saves lives when eaten in large amounts!"},"key":4721196,"metrics":{"bounce-rate":88.29,"hits":2942,"sessions":2238}},{"fields":{"published":"2018-01-04T22:45:05Z","referrer.host":[{"key":"examplekittens.com","value":2716},{"key":"toppuppies.co.uk","value":3},{"key":"www.my-daily-news-site-times.com","value":3},{"key":"yahoo.com","value":2}],"segment":{"path":"news/","slug":"news"},"title":"Something interesting and witty"},"key":4718623,"metrics":{"bounce-rate":81.28,"hits":1650,"sessions":1368}}],"dimensions":["article.id"],"fields":{"referrer.host":[{"key":"toppuppies.co.uk","value":24848},{"key":"examplekittens.com","value":8193},{"key":"www.my-daily-news-site-times.com","value":213},{"key":"news.ing.example.com","value":196},{"key":"placekitten.com","value":68},{"key":"apple.com","value":59},{"key":"news.example.ca","value":34},{"key":"t.co","value":14},{"key":"www-my-daily-news-site-times-com.cdn.ampproject.org","value":5},{"key":"yahoo.com","value":2}]},"key":"2018-01-07T00:00:00.000Z","metrics":{"bounce-rate":84.76,"hits":20938,"sessions":16104}},{"details":[{"fields":{"published":"2018-01-06T15:17:26Z","referrer.host":[{"key":"toppuppies.co.uk","value":1330},{"key":"www.my-daily-news-site-times.com","value":46},{"key":"examplekittens.com","value":18},{"key":"www-my-daily-news-site-times-com.cdn.ampproject.org","value":16},{"key":"t.umblr.com","value":13}],"segment":{"path":"","slug":""},"title":"Icecream saves lives when eaten in large amounts!"},"key":4721196,"metrics":{"bounce-rate":71.94,"hits":1028,"sessions":852}},{"fields":{"published":"2018-01-06T04:18:29Z","referrer.host":[{"key":"toppuppies.co.uk","value":2129},{"key":"m.example.com","value":30},{"key":"www.my-daily-news-site-times.com","value":24},{"key":"examplekittens.com","value":8},{"key":"apple.com","value":7}],"segment":{"path":"news/","slug":"news"},"title":"The JSON Formatter was created to help with debugging. As JSON data is often output without line breaks to save space, it is extremely difficult to actually read and make sense of it."},"key":4720790,"metrics":{"bounce-rate":81.45,"hits":1382,"sessions":976}},{"fields":{"published":"2018-01-05T23:50:01Z","referrer.host":[{"key":"toppuppies.co.uk","value":387},{"key":"placekitten.com","value":118},{"key":"www.my-daily-news-site-times.com","value":11},{"key":"examplekittens.com","value":10},{"key":"apple.com.ng","value":2}],"segment":{"path":"","slug":""},"title":"Is Trump Fit For Office? 100 Percent Of Trump\u0026#8217;s Acquaintances Questioned This When Interviewed, Claims Author"},"key":4720446,"metrics":{"bounce-rate":79.22,"hits":357,"sessions":231}},{"fields":{"published":"2018-01-05T15:10:39Z","referrer.host":[{"key":"toppuppies.co.uk","value":52},{"key":"apple.com","value":48},{"key":"placekitten.com","value":23},{"key":"www.my-daily-news-site-times.com","value":9},{"key":"www-my-daily-news-site-times-com.cdn.ampproject.org","value":5}],"segment":{"path":"","slug":""},"title":" This little tool hoped to solve the problem by formatting the JSON data so that it is easy to read and debug by human beings."},"key":4719539,"metrics":{"bounce-rate":75.9,"hits":136,"sessions":83}},{"fields":{"published":"2018-01-04T22:45:05Z","referrer.host":[{"key":"examplekittens.com","value":3909},{"key":"toppuppies.co.uk","value":46},{"key":"m.example.com","value":2},{"key":"yahoo.com","value":2},{"key":"example.com","value":1}],"segment":{"path":"news/","slug":"news"},"title":"Something interesting and witty"},"key":4718623,"metrics":{"bounce-rate":82.63,"hits":2439,"sessions":2062}}],"dimensions":["article.id"],"fields":{"referrer.host":[{"key":"examplekittens.com","value":3945},{"key":"toppuppies.co.uk","value":3944},{"key":"placekitten.com","value":141},{"key":"www.my-daily-news-site-times.com","value":90},{"key":"apple.com","value":55},{"key":"m.example.com","value":32},{"key":"www-my-daily-news-site-times-com.cdn.ampproject.org","value":21},{"key":"t.umblr.com","value":13},{"key":"yahoo.com","value":2},{"key":"apple.com.ng","value":2},{"key":"example.com","value":1}]},"key":"2018-01-06T00:00:00.000Z","metrics":{"bounce-rate":79.87,"hits":5342,"sessions":4204}},{"details":[{"fields":{"published":"2018-01-04T22:45:05Z","referrer.host":[{"key":"examplekittens.com","value":2263},{"key":"toppuppies.co.uk","value":2180},{"key":"www.my-daily-news-site-times.com","value":29},{"key":"www-my-daily-news-site-times-com.cdn.ampproject.org","value":13},{"key":"t.co","value":4}],"segment":{"path":"news/","slug":"news"},"title":"Something interesting and witty"},"key":4718623,"metrics":{"bounce-rate":87.63,"hits":2730,"sessions":2248}},{"fields":{"published":"2018-01-04T20:20:19Z","referrer.host":[{"key":"toppuppies.co.uk","value":60},{"key":"m.example.com","value":14},{"key":"examplekittens.com","value":11},{"key":"www.my-daily-news-site-times.com","value":10},{"key":"l.facebook.com","value":6}],"segment":{"path":"","slug":""},"title":"North Korean Missile Nose Dives Into Own City, Twitter Roars With Possibility Of Kim Jong Un Nuking Himself"},"key":4718294,"metrics":{"bounce-rate":91.09,"hits":176,"sessions":146}},{"fields":{"published":"2018-01-04T16:14:00Z","referrer.host":[{"key":"toppuppies.co.uk","value":1967},{"key":"examplekittens.com","value":48},{"key":"apple.com","value":12},{"key":"placekitten.com","value":9},{"key":"www.my-daily-news-site-times.com","value":6}],"segment":{"path":"","slug":""},"title":"Shortly after it was created, JSON validation was added following the description set out by Douglas Crockford of json.org in RFC 4627. It has since been expanded to also validate both current competing JSON standards RFC 7159 and ECMA-404."},"key":4717833,"metrics":{"bounce-rate":91.09,"hits":1263,"sessions":898}},{"fields":{"published":"2018-01-03T21:20:10Z","referrer.host":[{"key":"toppuppies.co.uk","value":489},{"key":"www.my-daily-news-site-times.com","value":19},{"key":"placekitten.com","value":9},{"key":"www-my-daily-news-site-times-com.cdn.ampproject.org","value":5},{"key":"l.facebook.com","value":2}],"segment":{"path":"","slug":""},"title":"I'm running out of fake headlines, so let's have a few real ones!"},"key":4714872,"metrics":{"bounce-rate":89.03,"hits":335,"sessions":228}},{"fields":{"published":"2018-01-03T13:38:28Z","referrer.host":[{"key":"examplekittens.com","value":752},{"key":"t.co","value":2},{"key":"www.my-daily-news-site-times.com","value":1}],"segment":{"path":"news/","slug":"news"},"title":"MLorem ipsum delor sit amet"},"key":4714463,"metrics":{"bounce-rate":86.79,"hits":464,"sessions":409}}],"dimensions":["article.id"],"fields":{"referrer.host":[{"key":"toppuppies.co.uk","value":4696},{"key":"examplekittens.com","value":3074},{"key":"www.my-daily-news-site-times.com","value":65},{"key":"www-my-daily-news-site-times-com.cdn.ampproject.org","value":18},{"key":"placekitten.com","value":18},{"key":"m.example.com","value":14},{"key":"apple.com","value":12},{"key":"l.facebook.com","value":8},{"key":"t.co","value":6}]},"key":"2018-01-05T00:00:00.000Z","metrics":{"bounce-rate":88.54,"hits":4968,"sessions":3929}},{"details":[{"fields":{"published":"2018-01-04T16:14:00Z","referrer.host":[{"key":"toppuppies.co.uk","value":3612},{"key":"examplekittens.com","value":71},{"key":"www.my-daily-news-site-times.com","value":26},{"key":"apple.com","value":13},{"key":"news.ing.example.com.au","value":9}],"segment":{"path":"","slug":""},"title":"Shortly after it was created, JSON validation was added following the description set out by Douglas Crockford of json.org in RFC 4627. It has since been expanded to also validate both current competing JSON standards RFC 7159 and ECMA-404."},"key":4717833,"metrics":{"bounce-rate":70.19,"hits":2157,"sessions":1879}},{"fields":{"published":"2018-01-04T01:33:57Z","referrer.host":[{"key":"toppuppies.co.uk","value":539},{"key":"placekitten.com","value":13},{"key":"m.example.com","value":2},{"key":"route.overnewser.com","value":2},{"key":"www.my-daily-news-site-times.com","value":1}],"segment":{"path":"life/","slug":"life"},"title":"Classes Starting In NYC Sparks Woes Online Of Seeing Stuff You Shouldn\u0026#8217;t See"},"key":4715635,"metrics":{"bounce-rate":80.52,"hits":327,"sessions":267}},{"fields":{"published":"2018-01-03T21:20:10Z","referrer.host":[{"key":"toppuppies.co.uk","value":2680},{"key":"www.my-daily-news-site-times.com","value":25},{"key":"examplekittens.com","value":7},{"key":"apple.com","value":6},{"key":"m.example.com","value":4}],"segment":{"path":"","slug":""},"title":"I'm running out of fake headlines, so let's have a few real ones!"},"key":4714872,"metrics":{"bounce-rate":77.97,"hits":1637,"sessions":1203}},{"fields":{"published":"2018-01-03T15:40:29Z","referrer.host":[{"key":"toppuppies.co.uk","value":152},{"key":"examplekittens.com","value":57},{"key":"apple.com","value":24},{"key":"www.example.ae","value":4},{"key":"placekitten.com","value":2}],"segment":{"path":"","slug":""},"title":"Donald Trump Ripped For Weight Gain On Social Media, And Some Folks Aren\u0026#8217;t Very Nice"},"key":4714713,"metrics":{"bounce-rate":83.78,"hits":173,"sessions":148}},{"fields":{"published":"2018-01-03T13:38:28Z","referrer.host":[{"key":"examplekittens.com","value":493},{"key":"l.facebook.com","value":2},{"key":"t.co","value":2}],"segment":{"path":"news/","slug":"news"},"title":"MLorem ipsum delor sit amet"},"key":4714463,"metrics":{"bounce-rate":86.56,"hits":309,"sessions":268}}],"dimensions":["article.id"],"fields":{"referrer.host":[{"key":"toppuppies.co.uk","value":6983},{"key":"examplekittens.com","value":628},{"key":"www.my-daily-news-site-times.com","value":52},{"key":"apple.com","value":43},{"key":"placekitten.com","value":15},{"key":"news.ing.example.com.au","value":9},{"key":"m.example.com","value":6},{"key":"www.example.ae","value":4},{"key":"l.facebook.com","value":2},{"key":"route.overnewser.com","value":2},{"key":"t.co","value":2}]},"key":"2018-01-04T00:00:00.000Z","metrics":{"bounce-rate":75.11,"hits":4603,"sessions":3765}}],"dimensions":["date","article.id"],"fields":{"identifier":"author-974","referrer.host":[{"key":"toppuppies.co.uk","value":43882},{"key":"examplekittens.com","value":17387},{"key":"www.my-daily-news-site-times.com","value":432},{"key":"placekitten.com","value":264},{"key":"news.ing.example.com","value":234},{"key":"apple.com","value":202},{"key":"m.example.com","value":54},{"key":"www-my-daily-news-site-times-com.cdn.ampproject.org","value":44},{"key":"news.example.ca","value":34},{"key":"t.co","value":22},{"key":"t.umblr.com","value":13},{"key":"www.linkedin.com","value":12},{"key":"l.facebook.com","value":10},{"key":"news.ing.example.com.au","value":9},{"key":"yahoo.com","value":4},{"key":"a.example.com","value":4},{"key":"www.example.ae","value":4},{"key":"www.topbuzz.com","value":4},{"key":"apple.com.ng","value":2},{"key":"route.overnewser.com","value":2},{"key":"example.com","value":1}]},"key":974,"metrics":{"bounce-rate":83.37,"hits":39025,"sessions":30509}},{"details":[{"details":[{"fields":{"published":"2018-01-07T19:49:23Z","referrer.host":[{"key":"toppuppies.co.uk","value":11986},{"key":"placekitten.com","value":81},{"key":"www.my-daily-news-site-times.com","value":13},{"key":"apple.com","value":8},{"key":"maybe.someone.used.bing.com","value":4}],"segment":{"path":"tech/","slug":"tech"},"title":"The McLaren 720S Finally Gets Smacked Down"},"key":4723000,"metrics":{"bounce-rate":94.61,"hits":6407,"sessions":5901}},{"fields":{"published":"2018-01-07T19:13:54Z","referrer.host":[{"key":"toppuppies.co.uk","value":241},{"key":"placekitten.com","value":61},{"key":"apple.com","value":10},{"key":"examplekittens.com","value":6},{"key":"t.co","value":2}],"segment":{"path":"tech/","slug":"tech"},"title":"Galaxy X: Samsung\u0026#8217;s Flexible Stunner Might Be Getting Apple\u0026#8217;s 3D Touch Technology"},"key":4722895,"metrics":{"bounce-rate":88.31,"hits":194,"sessions":154}},{"fields":{"published":"2018-01-07T08:25:34Z","referrer.host":[{"key":"toppuppies.co.uk","value":833},{"key":"placekitten.com","value":40},{"key":"apple.com","value":12},{"key":"www.owler.com","value":10},{"key":"maybe.someone.used.bing.com","value":6}],"segment":{"path":"tech/","slug":"tech"},"title":"Surface Phone: Microsoft Seems To Be Packing A Revolutionary Camera For Its Industry-Changing Mobile Device"},"key":4722284,"metrics":{"bounce-rate":92.79,"hits":535,"sessions":472}},{"fields":{"published":"2018-01-07T06:54:07Z","referrer.host":[{"key":"toppuppies.co.uk","value":5536},{"key":"placekitten.com","value":16},{"key":"unboxholics.com","value":8},{"key":"apple.com","value":8},{"key":"www.exampleapis.com","value":6}],"segment":{"path":"tech/","slug":"tech"},"title":"Samsung Galaxy S9: Final RAM And Storage Options"},"key":4722244,"metrics":{"bounce-rate":93.19,"hits":2986,"sessions":2702}},{"fields":{"published":"2018-01-04T19:31:28Z","referrer.host":[{"key":"examplekittens.com","value":95},{"key":"toppuppies.co.uk","value":21},{"key":"apple.com","value":2}],"segment":{"path":"tech/","slug":"tech"},"title":"Porsche Mission E Specs Have Been Leaked"},"key":4718252,"metrics":{"bounce-rate":86.48,"hits":87,"sessions":74}}],"dimensions":["article.id"],"fields":{"referrer.host":[{"key":"toppuppies.co.uk","value":18617},{"key":"placekitten.com","value":198},{"key":"examplekittens.com","value":101},{"key":"apple.com","value":40},{"key":"www.my-daily-news-site-times.com","value":13},{"key":"maybe.someone.used.bing.com","value":10},{"key":"www.owler.com","value":10},{"key":"unboxholics.com","value":8},{"key":"www.exampleapis.com","value":6},{"key":"t.co","value":2}]},"key":"2018-01-08T00:00:00.000Z","metrics":{"bounce-rate":93.93,"hits":10209,"sessions":9303}},{"details":[{"fields":{"published":"2018-01-07T19:49:23Z","referrer.host":[{"key":"toppuppies.co.uk","value":6696},{"key":"placekitten.com","value":36},{"key":"www.my-daily-news-site-times.com","value":11},{"key":"route.overnewser.com","value":2},{"key":"apple.com","value":2}],"segment":{"path":"tech/","slug":"tech"},"title":"The McLaren 720S Finally Gets Smacked Down"},"key":4723000,"metrics":{"bounce-rate":86.94,"hits":3552,"sessions":3271}},{"fields":{"published":"2018-01-07T19:13:54Z","referrer.host":[{"key":"toppuppies.co.uk","value":252},{"key":"placekitten.com","value":25},{"key":"t.co","value":8},{"key":"www.example.co.uk","value":8},{"key":"apple.com","value":8}],"segment":{"path":"tech/","slug":"tech"},"title":"Galaxy X: Samsung\u0026#8217;s Flexible Stunner Might Be Getting Apple\u0026#8217;s 3D Touch Technology"},"key":4722895,"metrics":{"bounce-rate":79.47,"hits":181,"sessions":151}},{"fields":{"published":"2018-01-07T08:25:34Z","referrer.host":[{"key":"toppuppies.co.uk","value":5787},{"key":"placekitten.com","value":292},{"key":"maybe.someone.used.bing.com","value":68},{"key":"apple.com","value":54},{"key":"www.example.co.in","value":28}],"segment":{"path":"tech/","slug":"tech"},"title":"Surface Phone: Microsoft Seems To Be Packing A Revolutionary Camera For Its Industry-Changing Mobile Device"},"key":4722284,"metrics":{"bounce-rate":87.46,"hits":3763,"sessions":3150}},{"fields":{"published":"2018-01-07T06:54:07Z","referrer.host":[{"key":"toppuppies.co.uk","value":23537},{"key":"placekitten.com","value":241},{"key":"apple.com","value":34},{"key":"www.my-daily-news-site-times.com","value":24},{"key":"t.co","value":22}],"segment":{"path":"tech/","slug":"tech"},"title":"Samsung Galaxy S9: Final RAM And Storage Options"},"key":4722244,"metrics":{"bounce-rate":91.02,"hits":12890,"sessions":11484}},{"fields":{"published":"2018-01-04T19:31:28Z","referrer.host":[{"key":"toppuppies.co.uk","value":173},{"key":"examplekittens.com","value":32},{"key":"placekitten.com","value":15},{"key":"www.my-daily-news-site-times.com","value":4},{"key":"www.example.be","value":3}],"segment":{"path":"tech/","slug":"tech"},"title":"Porsche Mission E Specs Have Been Leaked"},"key":4718252,"metrics":{"bounce-rate":89.91,"hits":138,"sessions":119}}],"dimensions":["article.id"],"fields":{"referrer.host":[{"key":"toppuppies.co.uk","value":36445},{"key":"placekitten.com","value":609},{"key":"apple.com","value":98},{"key":"maybe.someone.used.bing.com","value":68},{"key":"www.my-daily-news-site-times.com","value":39},{"key":"examplekittens.com","value":32},{"key":"t.co","value":30},{"key":"www.example.co.in","value":28},{"key":"www.example.co.uk","value":8},{"key":"www.example.be","value":3},{"key":"route.overnewser.com","value":2}]},"key":"2018-01-07T00:00:00.000Z","metrics":{"bounce-rate":89.56,"hits":20524,"sessions":18175}},{"details":[],"dimensions":["article.id"],"fields":{},"key":"2018-01-06T00:00:00.000Z","metrics":{"bounce-rate":0}},{"details":[{"fields":{"published":"2018-01-05T09:13:58Z","referrer.host":[{"key":"toppuppies.co.uk","value":1042},{"key":"www-my-daily-news-site-times-com.cdn.ampproject.org","value":42},{"key":"www.my-daily-news-site-times.com","value":31},{"key":"apple.com","value":15},{"key":"www.example.ca","value":6}],"segment":{"path":"entertainment/","slug":"entertainment"},"title":"\u0026#8216;My 600-lb Life\u0026#8217; James K Update: James Is Currently In The ICU, Fans Fear He Might Not Make It"},"key":4719148,"metrics":{"bounce-rate":84.9,"hits":806,"sessions":583}},{"fields":{"published":"2018-01-04T19:31:28Z","referrer.host":[{"key":"toppuppies.co.uk","value":5083},{"key":"placekitten.com","value":106},{"key":"examplekittens.com","value":17},{"key":"plus.url.ing.example.com","value":16},{"key":"maybe.someone.used.bing.com","value":12}],"segment":{"path":"tech/","slug":"tech"},"title":"Porsche Mission E Specs Have Been Leaked"},"key":4718252,"metrics":{"bounce-rate":93.25,"hits":2864,"sessions":2578}},{"fields":{"published":"2017-12-31T16:39:42Z","referrer.host":[{"key":"toppuppies.co.uk","value":59},{"key":"maybe.someone.used.bing.com","value":19},{"key":"www-my-daily-news-site-times-com.cdn.ampproject.org","value":4},{"key":"t.co","value":2},{"key":"www.my-daily-news-site-times.com","value":1}],"segment":{"path":"tech/","slug":"tech"},"title":"Surface Phone: Microsoft\u0026#8217;s Folding Game-Changer Might Run Andromeda OS, And Some Apps Are Now Supporting It"},"key":4710443,"metrics":{"bounce-rate":87.5,"hits":83,"sessions":72}},{"fields":{"published":"2017-12-27T18:27:47Z","referrer.host":[],"segment":{"path":"tech/","slug":"tech"},"title":"A Tesla Model S P100D Just Dueled A New Acura NSX In A One-Fourth-Mile Race, \u0026#038; The Results Were Pretty Amazing"},"key":4704716,"metrics":{"bounce-rate":77.14,"hits":40,"sessions":35}},{"fields":{"published":"2017-12-09T06:38:23Z","referrer.host":[{"key":"www-my-daily-news-site-times-com.cdn.ampproject.org","value":40},{"key":"www.my-daily-news-site-times.com","value":19},{"key":"apple.com","value":18},{"key":"example.com","value":5},{"key":"www.reddit.com","value":5}],"segment":{"path":"entertainment/","slug":"entertainment"},"title":"JSON data can be generated and parsed with a wide variety of programming languages including JavaScript, PHP, Python, Ruby and Java."},"key":4673974,"metrics":{"bounce-rate":73.68,"hits":83,"sessions":38}}],"dimensions":["article.id"],"fields":{"referrer.host":[{"key":"toppuppies.co.uk","value":6184},{"key":"placekitten.com","value":106},{"key":"www-my-daily-news-site-times-com.cdn.ampproject.org","value":86},{"key":"www.my-daily-news-site-times.com","value":51},{"key":"apple.com","value":33},{"key":"maybe.someone.used.bing.com","value":31},{"key":"examplekittens.com","value":17},{"key":"plus.url.ing.example.com","value":16},{"key":"www.example.ca","value":6},{"key":"www.reddit.com","value":5},{"key":"example.com","value":5},{"key":"t.co","value":2}]},"key":"2018-01-05T00:00:00.000Z","metrics":{"bounce-rate":91.25,"hits":3876,"sessions":3306}},{"details":[{"fields":{"published":"2018-01-04T19:31:28Z","referrer.host":[{"key":"toppuppies.co.uk","value":1863},{"key":"placekitten.com","value":57},{"key":"route.overnewser.com","value":10},{"key":"apple.com","value":6},{"key":"www.my-daily-news-site-times.com","value":4}],"segment":{"path":"tech/","slug":"tech"},"title":"Porsche Mission E Specs Have Been Leaked"},"key":4718252,"metrics":{"bounce-rate":87.86,"hits":1013,"sessions":956}},{"fields":{"published":"2017-12-31T16:39:42Z","referrer.host":[{"key":"toppuppies.co.uk","value":41},{"key":"maybe.someone.used.bing.com","value":12},{"key":"www-my-daily-news-site-times-com.cdn.ampproject.org","value":4},{"key":"t.co","value":2},{"key":"apple.com.au","value":2}],"segment":{"path":"tech/","slug":"tech"},"title":"Surface Phone: Microsoft\u0026#8217;s Folding Game-Changer Might Run Andromeda OS, And Some Apps Are Now Supporting It"},"key":4710443,"metrics":{"bounce-rate":89.58,"hits":59,"sessions":48}},{"fields":{"published":"2017-12-24T02:57:04Z","referrer.host":[{"key":"toppuppies.co.uk","value":4},{"key":"www.linkedin.com","value":4},{"key":"t.co","value":2},{"key":"apple.com","value":2},{"key":"www-my-daily-news-site-times-com.cdn.ampproject.org","value":1}],"segment":{"path":"tech/","slug":"tech"},"title":"Surface Phone: Microsoft Might End Up Killing An Industry"},"key":4699941,"metrics":{"bounce-rate":90.9,"hits":13,"sessions":11}},{"fields":{"published":"2017-12-09T06:38:23Z","referrer.host":[{"key":"www-my-daily-news-site-times-com.cdn.ampproject.org","value":40},{"key":"apple.com","value":3},{"key":"m.example.com","value":2},{"key":"example.com","value":1},{"key":"www.my-daily-news-site-times.com","value":1}],"segment":{"path":"entertainment/","slug":"entertainment"},"title":"JSON data can be generated and parsed with a wide variety of programming languages including JavaScript, PHP, Python, Ruby and Java."},"key":4673974,"metrics":{"bounce-rate":77.77,"hits":34,"sessions":18}},{"fields":{"published":"2017-03-18T18:01:21Z","referrer.host":[{"key":"amp-reddit-com.cdn.ampproject.org","value":11},{"key":"yahoo.com","value":5},{"key":"start.att.net","value":2},{"key":"www-earnthenecklace-com.cdn.ampproject.org","value":2},{"key":"www-my-daily-news-site-times-com.cdn.ampproject.org","value":2}],"segment":{"path":"entertainment/","slug":"entertainment"},"title":"\u0026#8216;My 600lb Life\u0026#8217; Update: James K Is Alive, Regretting His Actions \u0026#038; Losing Weight"},"key":4069510,"metrics":{"bounce-rate":73.68,"hits":23,"sessions":19}}],"dimensions":["article.id"],"fields":{"referrer.host":[{"key":"toppuppies.co.uk","value":1908},{"key":"placekitten.com","value":57},{"key":"www-my-daily-news-site-times-com.cdn.ampproject.org","value":47},{"key":"maybe.someone.used.bing.com","value":12},{"key":"apple.com","value":11},{"key":"amp-reddit-com.cdn.ampproject.org","value":11},{"key":"route.overnewser.com","value":10},{"key":"www.my-daily-news-site-times.com","value":5},{"key":"yahoo.com","value":5},{"key":"www.linkedin.com","value":4},{"key":"t.co","value":4},{"key":"www-earnthenecklace-com.cdn.ampproject.org","value":2},{"key":"start.att.net","value":2},{"key":"apple.com.au","value":2},{"key":"m.example.com","value":2},{"key":"example.com","value":1}]},"key":"2018-01-04T00:00:00.000Z","metrics":{"bounce-rate":87.54,"hits":1142,"sessions":1052}}],"dimensions":["date","article.id"],"fields":{"identifier":"author-936","referrer.host":[{"key":"toppuppies.co.uk","value":63154},{"key":"placekitten.com","value":970},{"key":"apple.com","value":182},{"key":"examplekittens.com","value":150},{"key":"www-my-daily-news-site-times-com.cdn.ampproject.org","value":133},{"key":"maybe.someone.used.bing.com","value":121},{"key":"www.my-daily-news-site-times.com","value":108},{"key":"t.co","value":38},{"key":"www.example.co.in","value":28},{"key":"plus.url.ing.example.com","value":16},{"key":"route.overnewser.com","value":12},{"key":"amp-reddit-com.cdn.ampproject.org","value":11},{"key":"www.owler.com","value":10},{"key":"unboxholics.com","value":8},{"key":"www.example.co.uk","value":8},{"key":"www.exampleapis.com","value":6},{"key":"www.example.ca","value":6},{"key":"example.com","value":6},{"key":"yahoo.com","value":5},{"key":"www.reddit.com","value":5},{"key":"www.linkedin.com","value":4},{"key":"www.example.be","value":3},{"key":"apple.com.au","value":2},{"key":"www-earnthenecklace-com.cdn.ampproject.org","value":2},{"key":"m.example.com","value":2},{"key":"start.att.net","value":2}]},"key":936,"metrics":{"bounce-rate":90.95,"hits":35751,"sessions":31836}},{"details":[{"details":[{"fields":{"published":"2018-01-08T00:07:31Z","referrer.host":[{"key":"t.co","value":100},{"key":"toppuppies.co.uk","value":19},{"key":"www.my-daily-news-site-times.com","value":13},{"key":"apple.com","value":5},{"key":"placekitten.com","value":3}],"segment":{"path":"entertainment/","slug":"entertainment"},"title":"Watch 2018 Golden Globes Livestream: How To Find Video Of The Award Show And Red Carpet Live Online"},"key":4723361,"metrics":{"bounce-rate":86.04,"hits":110,"sessions":86}},{"fields":{"published":"2018-01-07T07:14:11Z","referrer.host":[{"key":"apple.com","value":159},{"key":"examplekittens.com","value":106},{"key":"toppuppies.co.uk","value":96},{"key":"maybe.someone.used.bing.com","value":21},{"key":"duckduckgo.com","value":16}],"segment":{"path":"","slug":""},"title":"Logan Paul Wanted For Questioning By Japanese Police, May Be Banned From Japan Amid More Misbehaving Video"},"key":4722226,"metrics":{"bounce-rate":91.46,"hits":321,"sessions":293}},{"fields":{"published":"2018-01-07T04:29:30Z","referrer.host":[{"key":"examplekittens.com","value":1404},{"key":"toppuppies.co.uk","value":140},{"key":"apple.com","value":50},{"key":"placekitten.com","value":14},{"key":"www.topbuzz.com","value":14}],"segment":{"path":"entertainment/","slug":"entertainment"},"title":"Megyn Kelly Could Be In Trouble On \u0026#8216;Today\u0026#8217; Show For Refusing To Interview Trump Tell-All Author Michael Wolff"},"key":4722207,"metrics":{"bounce-rate":86.21,"hits":1044,"sessions":914}},{"fields":{"published":"2018-01-06T22:49:12Z","referrer.host":[{"key":"toppuppies.co.uk","value":1726},{"key":"examplekittens.com","value":91},{"key":"www.my-daily-news-site-times.com","value":9},{"key":"www-my-daily-news-site-times-com.cdn.ampproject.org","value":5},{"key":"placekitten.com","value":2}],"segment":{"path":"","slug":""},"title":"Prince Harry And Royal Family \u0026#8216;Hate\u0026#8217; Donald Trump For Stalking Princess Diana, Bragging He Could\u0026#8217;ve Bedded Her"},"key":4721893,"metrics":{"bounce-rate":86.67,"hits":1087,"sessions":878}},{"fields":{"published":"2017-03-08T02:01:54Z","referrer.host":[{"key":"m.example.com","value":19},{"key":"l.facebook.com","value":2}],"segment":{"path":"","slug":""},"title":"Gigi Hadid And Zayn Malik Take Naked Selfie As Engagement Rumors Fly"},"key":4041984,"metrics":{"bounce-rate":92.39,"hits":97,"sessions":92}}],"dimensions":["article.id"],"fields":{"referrer.host":[{"key":"toppuppies.co.uk","value":1981},{"key":"examplekittens.com","value":1601},{"key":"apple.com","value":214},{"key":"t.co","value":100},{"key":"www.my-daily-news-site-times.com","value":22},{"key":"maybe.someone.used.bing.com","value":21},{"key":"m.example.com","value":19},{"key":"placekitten.com","value":19},{"key":"duckduckgo.com","value":16},{"key":"www.topbuzz.com","value":14},{"key":"www-my-daily-news-site-times-com.cdn.ampproject.org","value":5},{"key":"l.facebook.com","value":2}]},"key":"2018-01-08T00:00:00.000Z","metrics":{"bounce-rate":87.31,"hits":2659,"sessions":2263}},{"details":[{"fields":{"published":"2018-01-07T07:14:11Z","referrer.host":[{"key":"toppuppies.co.uk","value":1665},{"key":"examplekittens.com","value":54},{"key":"apple.com","value":42},{"key":"apple.news","value":18},{"key":"www.my-daily-news-site-times.com","value":15}],"segment":{"path":"","slug":""},"title":"Logan Paul Wanted For Questioning By Japanese Police, May Be Banned From Japan Amid More Misbehaving Video"},"key":4722226,"metrics":{"bounce-rate":79.33,"hits":1178,"sessions":842}},{"fields":{"published":"2018-01-07T04:29:30Z","referrer.host":[{"key":"examplekittens.com","value":6247},{"key":"toppuppies.co.uk","value":4150},{"key":"apple.com","value":76},{"key":"placekitten.com","value":50},{"key":"www.my-daily-news-site-times.com","value":41}],"segment":{"path":"entertainment/","slug":"entertainment"},"title":"Megyn Kelly Could Be In Trouble On \u0026#8216;Today\u0026#8217; Show For Refusing To Interview Trump Tell-All Author Michael Wolff"},"key":4722207,"metrics":{"bounce-rate":82.07,"hits":6873,"sessions":5389}},{"fields":{"published":"2018-01-06T22:49:12Z","referrer.host":[{"key":"toppuppies.co.uk","value":19178},{"key":"examplekittens.com","value":6260},{"key":"www.my-daily-news-site-times.com","value":167},{"key":"placekitten.com","value":63},{"key":"t.co","value":44}],"segment":{"path":"","slug":""},"title":"Prince Harry And Royal Family \u0026#8216;Hate\u0026#8217; Donald Trump For Stalking Princess Diana, Bragging He Could\u0026#8217;ve Bedded Her"},"key":4721893,"metrics":{"bounce-rate":81.19,"hits":15812,"sessions":12056}},{"fields":{"published":"2018-01-05T21:58:57Z","referrer.host":[{"key":"apple.com","value":104},{"key":"www.linkedin.com","value":13},{"key":"maybe.someone.used.bing.com","value":11},{"key":"m.example.com","value":10},{"key":"www.example.co.uk","value":6}],"segment":{"path":"news/","slug":"news"},"title":"Looking To Read \u0026#8216;Fire And Fury\u0026#8217; Online? Pirated PDF Versions Of Trump Tell-All Book Show Up As Demand Rises"},"key":4720430,"metrics":{"bounce-rate":83.78,"hits":176,"sessions":148}},{"fields":{"published":"2017-03-08T02:01:54Z","referrer.host":[{"key":"m.example.com","value":30},{"key":"l.facebook.com","value":2}],"segment":{"path":"","slug":""},"title":"Gigi Hadid And Zayn Malik Take Naked Selfie As Engagement Rumors Fly"},"key":4041984,"metrics":{"bounce-rate":92.77,"hits":275,"sessions":263}}],"dimensions":["article.id"],"fields":{"referrer.host":[{"key":"toppuppies.co.uk","value":24993},{"key":"examplekittens.com","value":12561},{"key":"www.my-daily-news-site-times.com","value":223},{"key":"apple.com","value":222},{"key":"placekitten.com","value":113},{"key":"t.co","value":44},{"key":"m.example.com","value":40},{"key":"apple.news","value":18},{"key":"www.linkedin.com","value":13},{"key":"maybe.someone.used.bing.com","value":11},{"key":"www.example.co.uk","value":6},{"key":"l.facebook.com","value":2}]},"key":"2018-01-07T00:00:00.000Z","metrics":{"bounce-rate":81.54,"hits":24314,"sessions":18698}},{"details":[{"fields":{"published":"2018-01-06T04:08:29Z","referrer.host":[{"key":"toppuppies.co.uk","value":71},{"key":"t.co","value":49},{"key":"apple.com","value":48},{"key":"www.my-daily-news-site-times.com","value":45},{"key":"examplekittens.com","value":25}],"segment":{"path":"life/","slug":"life"},"title":"Mega Millions Winning Numbers: Finding Winning Combination For January 5 Drawing Worth $450 Million"},"key":4720901,"metrics":{"bounce-rate":81.78,"hits":357,"sessions":258}},{"fields":{"published":"2018-01-06T03:35:49Z","referrer.host":[{"key":"toppuppies.co.uk","value":266},{"key":"duckduckgo.com","value":23},{"key":"maybe.someone.used.bing.com","value":18},{"key":"apple.com","value":13},{"key":"yahoo.com","value":10}],"segment":{"path":"life/","slug":"life"},"title":"Netflix Wants People To Stop Asking If They Have The Gorilla Channel After Fake Trump Book Excerpt Goes Viral"},"key":4720822,"metrics":{"bounce-rate":83.49,"hits":281,"sessions":206}},{"fields":{"published":"2018-01-05T21:58:57Z","referrer.host":[{"key":"apple.com","value":117},{"key":"toppuppies.co.uk","value":53},{"key":"maybe.someone.used.bing.com","value":14},{"key":"www.my-daily-news-site-times.com","value":12},{"key":"t.co","value":8}],"segment":{"path":"news/","slug":"news"},"title":"Looking To Read \u0026#8216;Fire And Fury\u0026#8217; Online? Pirated PDF Versions Of Trump Tell-All Book Show Up As Demand Rises"},"key":4720430,"metrics":{"bounce-rate":88.38,"hits":238,"sessions":198}},{"fields":{"published":"2018-01-04T23:58:40Z","referrer.host":[{"key":"bestbarkernews.com","value":200},{"key":"apple.com","value":34},{"key":"t.co","value":18},{"key":"toppuppies.co.uk","value":10},{"key":"yahoo.com","value":8}],"segment":{"path":"news/","slug":"news"},"title":"Mike Rogers To Retire: Director Of NSA Reportedly Plans To Retire Amid Trump Attacks On The Agency"},"key":4718903,"metrics":{"bounce-rate":90.77,"hits":229,"sessions":206}},{"fields":{"published":"2018-01-04T23:40:33Z","referrer.host":[{"key":"toppuppies.co.uk","value":1483},{"key":"examplekittens.com","value":42},{"key":"apple.com","value":26},{"key":"m.example.com","value":14},{"key":"t.co","value":10}],"segment":{"path":"","slug":""},"title":"Melania Trump Divorce Rumors: Tell-All Book Detailing Fights, Infidelity Sparks Rumors Of White House Breakup"},"key":4718864,"metrics":{"bounce-rate":85.59,"hits":1134,"sessions":951}}],"dimensions":["article.id"],"fields":{"referrer.host":[{"key":"toppuppies.co.uk","value":1883},{"key":"apple.com","value":238},{"key":"bestbarkernews.com","value":200},{"key":"t.co","value":85},{"key":"examplekittens.com","value":67},{"key":"www.my-daily-news-site-times.com","value":57},{"key":"maybe.someone.used.bing.com","value":32},{"key":"duckduckgo.com","value":23},{"key":"yahoo.com","value":18},{"key":"m.example.com","value":14}]},"key":"2018-01-06T00:00:00.000Z","metrics":{"bounce-rate":85.7,"hits":2239,"sessions":1819}},{"details":[{"fields":{"published":"2018-01-05T13:26:51Z","referrer.host":[{"key":"examplekittens.com","value":41},{"key":"www.my-daily-news-site-times.com","value":38},{"key":"apple.com","value":26},{"key":"toppuppies.co.uk","value":8},{"key":"yahoo.com","value":8}],"segment":{"path":"sports/","slug":"sports"},"title":"NFL Rumors: New England Patriots Dynasty Coming To End Amid Feud Between Tom Brady And Bill Belichick"},"key":4719551,"metrics":{"bounce-rate":86.11,"hits":166,"sessions":108}},{"fields":{"published":"2018-01-04T23:58:40Z","referrer.host":[{"key":"bestbarkernews.com","value":3081},{"key":"toppuppies.co.uk","value":245},{"key":"apple.com","value":110},{"key":"examplekittens.com","value":33},{"key":"www.reddit.com","value":32}],"segment":{"path":"news/","slug":"news"},"title":"Mike Rogers To Retire: Director Of NSA Reportedly Plans To Retire Amid Trump Attacks On The Agency"},"key":4718903,"metrics":{"bounce-rate":92.91,"hits":2113,"sessions":1934}},{"fields":{"published":"2018-01-04T23:40:33Z","referrer.host":[{"key":"toppuppies.co.uk","value":7303},{"key":"examplekittens.com","value":1073},{"key":"www.my-daily-news-site-times.com","value":130},{"key":"m.example.com","value":42},{"key":"www-my-daily-news-site-times-com.cdn.ampproject.org","value":30}],"segment":{"path":"","slug":""},"title":"Melania Trump Divorce Rumors: Tell-All Book Detailing Fights, Infidelity Sparks Rumors Of White House Breakup"},"key":4718864,"metrics":{"bounce-rate":86.78,"hits":5588,"sessions":4374}},{"fields":{"published":"2018-01-04T02:42:25Z","referrer.host":[{"key":"examplekittens.com","value":633},{"key":"toppuppies.co.uk","value":347},{"key":"www.my-daily-news-site-times.com","value":23},{"key":"t.co","value":22},{"key":"apple.com","value":4}],"segment":{"path":"news/","slug":"news"},"title":"White House In \u0026#8216;Total Meltdown\u0026#8217; After Book Detailed Trump\u0026#8217;s Infidelity, Public Fights With Melania"},"key":4716853,"metrics":{"bounce-rate":82.63,"hits":741,"sessions":593}},{"fields":{"published":"2017-12-27T06:00:53Z","referrer.host":[{"key":"apple.com","value":88},{"key":"yahoo.com","value":13},{"key":"maybe.someone.used.bing.com","value":5},{"key":"examplekittens.com","value":3},{"key":"www-my-daily-news-site-times-com.cdn.ampproject.org","value":3}],"segment":{"path":"","slug":""},"title":"Cardi B Sex Tape Video: Rapper And Boyfriend Offset Post Racy Clip To Instagram In Response To Real Video Leak"},"key":4703110,"metrics":{"bounce-rate":90.47,"hits":72,"sessions":63}}],"dimensions":["article.id"],"fields":{"referrer.host":[{"key":"toppuppies.co.uk","value":7903},{"key":"bestbarkernews.com","value":3081},{"key":"examplekittens.com","value":1783},{"key":"apple.com","value":228},{"key":"www.my-daily-news-site-times.com","value":191},{"key":"m.example.com","value":42},{"key":"www-my-daily-news-site-times-com.cdn.ampproject.org","value":33},{"key":"www.reddit.com","value":32},{"key":"t.co","value":22},{"key":"yahoo.com","value":21},{"key":"maybe.someone.used.bing.com","value":5}]},"key":"2018-01-05T00:00:00.000Z","metrics":{"bounce-rate":88.13,"hits":8680,"sessions":7072}},{"details":[{"fields":{"published":"2018-01-04T02:42:25Z","referrer.host":[{"key":"toppuppies.co.uk","value":3722},{"key":"examplekittens.com","value":1157},{"key":"www.my-daily-news-site-times.com","value":57},{"key":"apple.com","value":14},{"key":"yahoo.com","value":4}],"segment":{"path":"news/","slug":"news"},"title":"White House In \u0026#8216;Total Meltdown\u0026#8217; After Book Detailed Trump\u0026#8217;s Infidelity, Public Fights With Melania"},"key":4716853,"metrics":{"bounce-rate":83.6,"hits":2953,"sessions":2549}},{"fields":{"published":"2018-01-03T21:11:11Z","referrer.host":[{"key":"www.my-daily-news-site-times.com","value":8},{"key":"examplekittens.com","value":7},{"key":"toppuppies.co.uk","value":4},{"key":"m.example.com","value":2},{"key":"apple.com","value":2}],"segment":{"path":"news/","slug":"news"},"title":"Donald Trump Is \u0026#8216;Psychologically Unfit\u0026#8217; For Presidency After Nuclear Threat, Former Bush Ethics Lawyer Says"},"key":4715434,"metrics":{"bounce-rate":95,"hits":28,"sessions":20}},{"fields":{"published":"2018-01-01T04:15:21Z","referrer.host":[{"key":"apple.com","value":11},{"key":"yahoo.com","value":9},{"key":"maybe.someone.used.bing.com","value":4},{"key":"m.example.com","value":2},{"key":"search.abclauncher.com","value":2}],"segment":{"path":"life/","slug":"life"},"title":"Jenny McCarthy Plastic Surgery: New Year\u0026#8217;s Eve Appearance Has McCarthy Drawing Comparisons To Joan Rivers"},"key":4711286,"metrics":{"bounce-rate":82.6,"hits":25,"sessions":23}},{"fields":{"published":"2017-12-31T00:54:16Z","referrer.host":[{"key":"duckduckgo.com","value":11},{"key":"yahoo.com","value":10},{"key":"maybe.someone.used.bing.com","value":2},{"key":"www.my-daily-news-site-times.com","value":1}],"segment":{"path":"life/","slug":"life"},"title":"Niagara Falls Frozen: Late 2017 Cold Snap Has Falls Covered In Ice, See The Amazing Pictures"},"key":4709069,"metrics":{"bounce-rate":93.33,"hits":17,"sessions":15}},{"fields":{"published":"2017-07-05T20:20:03Z","referrer.host":[],"segment":{"path":"entertainment/","slug":"entertainment"},"title":"Chumlee Dead? \u0026#8216;Pawn Stars\u0026#8217; Actor Did Not Die Of A Marijuana Overdose, As Death Hoax Claims"},"key":4347882,"metrics":{"bounce-rate":88.88,"hits":9,"sessions":9}}],"dimensions":["article.id"],"fields":{"referrer.host":[{"key":"toppuppies.co.uk","value":3726},{"key":"examplekittens.com","value":1164},{"key":"www.my-daily-news-site-times.com","value":66},{"key":"apple.com","value":27},{"key":"yahoo.com","value":23},{"key":"duckduckgo.com","value":11},{"key":"maybe.someone.used.bing.com","value":6},{"key":"m.example.com","value":4},{"key":"search.abclauncher.com","value":2}]},"key":"2018-01-04T00:00:00.000Z","metrics":{"bounce-rate":83.75,"hits":3032,"sessions":2616}}],"dimensions":["date","article.id"],"fields":{"identifier":"author-90","referrer.host":[{"key":"toppuppies.co.uk","value":40486},{"key":"examplekittens.com","value":17176},{"key":"bestbarkernews.com","value":3281},{"key":"apple.com","value":929},{"key":"www.my-daily-news-site-times.com","value":559},{"key":"t.co","value":251},{"key":"placekitten.com","value":132},{"key":"m.example.com","value":119},{"key":"maybe.someone.used.bing.com","value":75},{"key":"yahoo.com","value":62},{"key":"duckduckgo.com","value":50},{"key":"www-my-daily-news-site-times-com.cdn.ampproject.org","value":38},{"key":"www.reddit.com","value":32},{"key":"apple.news","value":18},{"key":"www.topbuzz.com","value":14},{"key":"www.linkedin.com","value":13},{"key":"www.example.co.uk","value":6},{"key":"l.facebook.com","value":4},{"key":"search.abclauncher.com","value":2}]},"key":90,"metrics":{"bounce-rate":83.79,"hits":40924,"sessions":32468}},{"details":[{"details":[{"fields":{"published":"2018-01-06T12:06:20Z","referrer.host":[{"key":"toppuppies.co.uk","value":10379},{"key":"www.my-daily-news-site-times.com","value":64},{"key":"examplekittens.com","value":38},{"key":"apple.com","value":26},{"key":"yahoo.com","value":22}],"segment":{"path":"","slug":""},"title":"Jennifer Aniston And Brad Pitt Reportedly Got Caught Planning A Secret Reunion"},"key":4721145,"metrics":{"bounce-rate":86.88,"hits":6103,"sessions":4742}},{"fields":{"published":"2018-01-03T11:52:40Z","referrer.host":[{"key":"www-my-daily-news-site-times-com.cdn.ampproject.org","value":3},{"key":"maybe.someone.used.bing.com","value":2},{"key":"www.example.ca","value":2},{"key":"www.example.co.in","value":2},{"key":"apple.com.au","value":2}],"segment":{"path":"","slug":""},"title":"Jennifer Aniston And Justin Theroux Reportedly Think Spending Time Apart Is Healthy"},"key":4714435,"metrics":{"bounce-rate":72.72,"hits":17,"sessions":11}},{"fields":{"published":"2017-12-28T10:04:26Z","referrer.host":[{"key":"www-my-daily-news-site-times-com.cdn.ampproject.org","value":10},{"key":"www.my-daily-news-site-times.com","value":3},{"key":"duckduckgo.com","value":2},{"key":"yahoo.com","value":2},{"key":"search.yahoo.com","value":2}],"segment":{"path":"","slug":""},"title":"Jennifer Aniston And Justin Theroux Are Reportedly Heading For Divorce After Major Fight"},"key":4705682,"metrics":{"bounce-rate":73.33,"hits":22,"sessions":15}},{"fields":{"published":"2017-12-20T13:58:20Z","referrer.host":[{"key":"maybe.someone.used.bing.com","value":3},{"key":"example.com","value":2},{"key":"www.example.co.uk","value":2},{"key":"apple.com","value":2}],"segment":{"path":"","slug":""},"title":"Did Jennifer Aniston And Justin Theroux Split? Couple Spotted Shopping Separately"},"key":4693579,"metrics":{"bounce-rate":100,"hits":9,"sessions":4}},{"fields":{"published":"2017-11-06T12:26:14Z","referrer.host":[{"key":"maybe.someone.used.bing.com","value":6},{"key":"yahoo.com","value":5},{"key":"frontpage.pch.com","value":2},{"key":"r.search.aol.com","value":2}],"segment":{"path":"","slug":""},"title":"Jennifer Aniston, Justin Theroux Baby News: Actress Is Reportedly Pregnant \u0026#038; May Adopt Too"},"key":4601217,"metrics":{"bounce-rate":71.42,"hits":8,"sessions":7}}],"dimensions":["article.id"],"fields":{"referrer.host":[{"key":"toppuppies.co.uk","value":10379},{"key":"www.my-daily-news-site-times.com","value":67},{"key":"examplekittens.com","value":38},{"key":"yahoo.com","value":29},{"key":"apple.com","value":28},{"key":"www-my-daily-news-site-times-com.cdn.ampproject.org","value":13},{"key":"maybe.someone.used.bing.com","value":11},{"key":"search.yahoo.com","value":2},{"key":"example.com","value":2},{"key":"frontpage.pch.com","value":2},{"key":"www.example.co.in","value":2},{"key":"www.example.ca","value":2},{"key":"duckduckgo.com","value":2},{"key":"www.example.co.uk","value":2},{"key":"r.search.aol.com","value":2},{"key":"apple.com.au","value":2}]},"key":"2018-01-07T00:00:00.000Z","metrics":{"bounce-rate":86.79,"hits":6159,"sessions":4779}},{"details":[{"fields":{"published":"2018-01-06T12:06:20Z","referrer.host":[{"key":"toppuppies.co.uk","value":51958},{"key":"www.my-daily-news-site-times.com","value":125},{"key":"apple.com","value":44},{"key":"www-my-daily-news-site-times-com.cdn.ampproject.org","value":34},{"key":"t.co","value":18}],"segment":{"path":"","slug":""},"title":"Jennifer Aniston And Brad Pitt Reportedly Got Caught Planning A Secret Reunion"},"key":4721145,"metrics":{"bounce-rate":83.91,"hits":28698,"sessions":24336}},{"fields":{"published":"2018-01-03T11:52:40Z","referrer.host":[{"key":"yahoo.com","value":2},{"key":"maybe.someone.used.bing.com","value":2},{"key":"apple.com","value":2},{"key":"www.my-daily-news-site-times.com","value":1}],"segment":{"path":"","slug":""},"title":"Jennifer Aniston And Justin Theroux Reportedly Think Spending Time Apart Is Healthy"},"key":4714435,"metrics":{"bounce-rate":88.23,"hits":22,"sessions":17}},{"fields":{"published":"2017-12-28T10:04:26Z","referrer.host":[{"key":"www-my-daily-news-site-times-com.cdn.ampproject.org","value":12},{"key":"yahoo.com","value":6},{"key":"toppuppies.co.uk","value":4},{"key":"maybe.someone.used.bing.com","value":3},{"key":"r.search.aol.com","value":2}],"segment":{"path":"","slug":""},"title":"Jennifer Aniston And Justin Theroux Are Reportedly Heading For Divorce After Major Fight"},"key":4705682,"metrics":{"bounce-rate":52.17,"hits":42,"sessions":23}},{"fields":{"published":"2017-12-26T10:08:25Z","referrer.host":[{"key":"apple.com","value":8},{"key":"www.my-daily-news-site-times.com","value":1}],"segment":{"path":"","slug":""},"title":"Amber Heard And Elon Musk Were Caught Kissing Despite Confirming Split"},"key":4701949,"metrics":{"bounce-rate":75,"hits":7,"sessions":4}},{"fields":{"published":"2017-12-20T13:58:20Z","referrer.host":[{"key":"example.com","value":3},{"key":"www.example.co.in","value":2}],"segment":{"path":"","slug":""},"title":"Did Jennifer Aniston And Justin Theroux Split? Couple Spotted Shopping Separately"},"key":4693579,"metrics":{"bounce-rate":60,"hits":7,"sessions":5}}],"dimensions":["article.id"],"fields":{"referrer.host":[{"key":"toppuppies.co.uk","value":51962},{"key":"www.my-daily-news-site-times.com","value":127},{"key":"apple.com","value":54},{"key":"www-my-daily-news-site-times-com.cdn.ampproject.org","value":46},{"key":"t.co","value":18},{"key":"yahoo.com","value":8},{"key":"maybe.someone.used.bing.com","value":5},{"key":"example.com","value":3},{"key":"www.example.co.in","value":2},{"key":"r.search.aol.com","value":2}]},"key":"2018-01-06T00:00:00.000Z","metrics":{"bounce-rate":83.87,"hits":28776,"sessions":24385}}],"dimensions":["date","article.id"],"fields":{"identifier":"author-785","referrer.host":[{"key":"toppuppies.co.uk","value":62341},{"key":"www.my-daily-news-site-times.com","value":194},{"key":"apple.com","value":82},{"key":"www-my-daily-news-site-times-com.cdn.ampproject.org","value":59},{"key":"examplekittens.com","value":38},{"key":"yahoo.com","value":37},{"key":"t.co","value":18},{"key":"maybe.someone.used.bing.com","value":16},{"key":"example.com","value":5},{"key":"www.example.co.in","value":4},{"key":"r.search.aol.com","value":4},{"key":"search.yahoo.com","value":2},{"key":"www.example.co.uk","value":2},{"key":"duckduckgo.com","value":2},{"key":"frontpage.pch.com","value":2},{"key":"www.example.ca","value":2},{"key":"apple.com.au","value":2}]},"key":785,"metrics":{"bounce-rate":84.35,"hits":34935,"sessions":29164}},{"details":[{"details":[{"fields":{"published":"2018-01-08T00:29:25Z","referrer.host":[{"key":"toppuppies.co.uk","value":547},{"key":"apple.com","value":72},{"key":"placekitten.com","value":14},{"key":"apple.com.au","value":10},{"key":"www.my-daily-news-site-times.com","value":9}],"segment":{"path":"news/","slug":"news"},"title":"WikiLeaks Publishes \u0026#8216;Fire And Fury\u0026#8217; Book To Read Free Online: Full 327-Page PDF Of Real Book May Hurt Sales"},"key":4723379,"metrics":{"bounce-rate":84.17,"hits":403,"sessions":316}},{"fields":{"published":"2018-01-07T18:57:41Z","referrer.host":[{"key":"toppuppies.co.uk","value":1046},{"key":"examplekittens.com","value":370},{"key":"apple.com","value":21},{"key":"www.my-daily-news-site-times.com","value":5},{"key":"news.ing.example.com","value":2}],"segment":{"path":"life/","slug":"life"},"title":"Apples taste good."},"key":4722853,"metrics":{"bounce-rate":89.84,"hits":841,"sessions":709}},{"fields":{"published":"2018-01-06T19:50:44Z","referrer.host":[{"key":"toppuppies.co.uk","value":38},{"key":"news.ing.example.com","value":20},{"key":"apple.com","value":17},{"key":"news.ing.example.com.au","value":6},{"key":"www.my-daily-news-site-times.com","value":5}],"segment":{"path":"","slug":""},"title":"Melania Trump Suffered \u0026#8216;Sharp And Peremptory\u0026#8217; Words From Her Husband On Jan. 20, Per \u0026#8216;Fire And Fury\u0026#8217; Book"},"key":4721524,"metrics":{"bounce-rate":86.53,"hits":65,"sessions":52}},{"fields":{"published":"2018-01-05T17:02:04Z","referrer.host":[{"key":"toppuppies.co.uk","value":107},{"key":"www.my-daily-news-site-times.com","value":8},{"key":"apple.com","value":6},{"key":"yahoo.com","value":2},{"key":"tatrenutek.si","value":2}],"segment":{"path":"","slug":""},"title":"Melania Trump\u0026#8217;s Racy \u0026#8216;New York Post\u0026#8217; Leaked Photos \u0026#8211; Everybody Assumed Donald Was Leaker, Melania Inconsolable"},"key":4719890,"metrics":{"bounce-rate":91.54,"hits":82,"sessions":71}},{"fields":{"published":"2017-12-12T16:30:50Z","referrer.host":[{"key":"yahoo.com","value":43},{"key":"maybe.someone.used.bing.com","value":21},{"key":"duckduckgo.com","value":4},{"key":"start.att.net","value":4},{"key":"www.letsrun.com","value":3}],"segment":{"path":"news/","slug":"news"},"title":"\u0026#8216;Jami Cantor Photos\u0026#8217; Searches Spike As Former NFL Network Wardrobe Stylist Sues For Sexual Misconduct"},"key":4679688,"metrics":{"bounce-rate":85.71,"hits":47,"sessions":42}}],"dimensions":["article.id"],"fields":{"referrer.host":[{"key":"toppuppies.co.uk","value":1738},{"key":"examplekittens.com","value":370},{"key":"apple.com","value":116},{"key":"yahoo.com","value":45},{"key":"www.my-daily-news-site-times.com","value":27},{"key":"news.ing.example.com","value":22},{"key":"maybe.someone.used.bing.com","value":21},{"key":"placekitten.com","value":14},{"key":"apple.com.au","value":10},{"key":"news.ing.example.com.au","value":6},{"key":"duckduckgo.com","value":4},{"key":"start.att.net","value":4},{"key":"www.letsrun.com","value":3},{"key":"tatrenutek.si","value":2}]},"key":"2018-01-08T00:00:00.000Z","metrics":{"bounce-rate":88.15,"hits":1438,"sessions":1190}},{"details":[{"fields":{"published":"2018-01-07T18:57:41Z","referrer.host":[{"key":"toppuppies.co.uk","value":1102},{"key":"examplekittens.com","value":245},{"key":"t.co","value":24},{"key":"apple.com","value":18},{"key":"news.ing.example.com","value":14}],"segment":{"path":"life/","slug":"life"},"title":"Apples taste good."},"key":4722853,"metrics":{"bounce-rate":74.72,"hits":855,"sessions":736}},{"fields":{"published":"2018-01-06T19:50:44Z","referrer.host":[{"key":"toppuppies.co.uk","value":429},{"key":"news.ing.example.com","value":38},{"key":"apple.com","value":25},{"key":"www.my-daily-news-site-times.com","value":25},{"key":"placekitten.com","value":21}],"segment":{"path":"","slug":""},"title":"Melania Trump Suffered \u0026#8216;Sharp And Peremptory\u0026#8217; Words From Her Husband On Jan. 20, Per \u0026#8216;Fire And Fury\u0026#8217; Book"},"key":4721524,"metrics":{"bounce-rate":67.64,"hits":590,"sessions":340}},{"fields":{"published":"2018-01-06T16:36:41Z","referrer.host":[{"key":"examplekittens.com","value":446},{"key":"news.ing.example.com","value":31},{"key":"apple.com","value":11},{"key":"toppuppies.co.uk","value":8},{"key":"yahoo.com","value":8}],"segment":{"path":"","slug":""},"title":"Trump Makes White House Staff, Interns Buy \u0026#8216;Fire And Fury\u0026#8217; Books To \u0026#8216;Dispose Of Them,\u0026#8217; But Forgets PDF, Kindle"},"key":4721416,"metrics":{"bounce-rate":77.97,"hits":371,"sessions":277}},{"fields":{"published":"2018-01-06T15:49:58Z","referrer.host":[{"key":"examplekittens.com","value":582},{"key":"toppuppies.co.uk","value":87},{"key":"apple.com","value":17},{"key":"t.co","value":12},{"key":"www.my-daily-news-site-times.com","value":12}],"segment":{"path":"news/","slug":"news"},"title":"Trump Claims He Ran For President Only Once, But \u0026#8216;Associated Press\u0026#8217; Has Receipts, Photos Of Trump\u0026#8217;s 2000 Run"},"key":4721343,"metrics":{"bounce-rate":84.45,"hits":471,"sessions":386}},{"fields":{"published":"2018-01-05T17:02:04Z","referrer.host":[{"key":"toppuppies.co.uk","value":3880},{"key":"www.my-daily-news-site-times.com","value":35},{"key":"apple.com","value":20},{"key":"www-my-daily-news-site-times-com.cdn.ampproject.org","value":8},{"key":"tatrenutek.si","value":4}],"segment":{"path":"","slug":""},"title":"Melania Trump\u0026#8217;s Racy \u0026#8216;New York Post\u0026#8217; Leaked Photos \u0026#8211; Everybody Assumed Donald Was Leaker, Melania Inconsolable"},"key":4719890,"metrics":{"bounce-rate":88.25,"hits":2297,"sessions":1865}}],"dimensions":["article.id"],"fields":{"referrer.host":[{"key":"toppuppies.co.uk","value":5506},{"key":"examplekittens.com","value":1273},{"key":"apple.com","value":91},{"key":"news.ing.example.com","value":83},{"key":"www.my-daily-news-site-times.com","value":72},{"key":"t.co","value":36},{"key":"placekitten.com","value":21},{"key":"www-my-daily-news-site-times-com.cdn.ampproject.org","value":8},{"key":"yahoo.com","value":8},{"key":"tatrenutek.si","value":4}]},"key":"2018-01-07T00:00:00.000Z","metrics":{"bounce-rate":82.35,"hits":4584,"sessions":3604}},{"details":[{"fields":{"published":"2018-01-05T20:26:25Z","referrer.host":[{"key":"toppuppies.co.uk","value":12815},{"key":"examplekittens.com","value":497},{"key":"www.my-daily-news-site-times.com","value":46},{"key":"t.co","value":24},{"key":"m.example.com","value":17}],"segment":{"path":"","slug":""},"title":"Trump Thinks Husband And Wife Should Do Their \u0026#8216;Own Thing,\u0026#8217; Alleges New Book"},"key":4720008,"metrics":{"bounce-rate":84.74,"hits":8043,"sessions":5809}},{"fields":{"published":"2018-01-05T17:02:04Z","referrer.host":[{"key":"toppuppies.co.uk","value":39057},{"key":"www.my-daily-news-site-times.com","value":264},{"key":"apple.com","value":41},{"key":"cdn.example.com","value":27},{"key":"www-my-daily-news-site-times-com.cdn.ampproject.org","value":15}],"segment":{"path":"","slug":""},"title":"Melania Trump\u0026#8217;s Racy \u0026#8216;New York Post\u0026#8217; Leaked Photos \u0026#8211; Everybody Assumed Donald Was Leaker, Melania Inconsolable"},"key":4719890,"metrics":{"bounce-rate":88.19,"hits":22608,"sessions":17884}},{"fields":{"published":"2018-01-05T16:19:28Z","referrer.host":[{"key":"examplekittens.com","value":2002},{"key":"toppuppies.co.uk","value":238},{"key":"apple.com","value":70},{"key":"www.my-daily-news-site-times.com","value":23},{"key":"apple.com.au","value":18}],"segment":{"path":"","slug":""},"title":"Ivanka Trump Has \u0026#8216;Distaste For Her Stepmother\u0026#8217; Melania Trump, Shared Quote About FLOTUS With Friends"},"key":4719829,"metrics":{"bounce-rate":75.39,"hits":1981,"sessions":1512}},{"fields":{"published":"2018-01-04T02:04:43Z","referrer.host":[{"key":"toppuppies.co.uk","value":1198},{"key":"www.my-daily-news-site-times.com","value":10},{"key":"maybe.someone.used.bing.com","value":5},{"key":"www.reddit.com","value":5},{"key":"m.example.com","value":4}],"segment":{"path":"","slug":""},"title":"Book: top 10 best dog photos from every country"},"key":4716668,"metrics":{"bounce-rate":91.14,"hits":774,"sessions":655}},{"fields":{"published":"2017-12-12T16:30:50Z","referrer.host":[{"key":"yahoo.com","value":627},{"key":"maybe.someone.used.bing.com","value":384},{"key":"duckduckgo.com","value":83},{"key":"apple.com","value":63},{"key":"r.search.aol.com","value":43}],"segment":{"path":"news/","slug":"news"},"title":"\u0026#8216;Jami Cantor Photos\u0026#8217; Searches Spike As Former NFL Network Wardrobe Stylist Sues For Sexual Misconduct"},"key":4679688,"metrics":{"bounce-rate":84.78,"hits":728,"sessions":644}}],"dimensions":["article.id"],"fields":{"referrer.host":[{"key":"toppuppies.co.uk","value":53308},{"key":"examplekittens.com","value":2499},{"key":"yahoo.com","value":627},{"key":"maybe.someone.used.bing.com","value":389},{"key":"www.my-daily-news-site-times.com","value":343},{"key":"apple.com","value":174},{"key":"duckduckgo.com","value":83},{"key":"r.search.aol.com","value":43},{"key":"cdn.example.com","value":27},{"key":"t.co","value":24},{"key":"m.example.com","value":21},{"key":"apple.com.au","value":18},{"key":"www-my-daily-news-site-times-com.cdn.ampproject.org","value":15},{"key":"www.reddit.com","value":5}]},"key":"2018-01-06T00:00:00.000Z","metrics":{"bounce-rate":86.7,"hits":34134,"sessions":26504}},{"details":[{"fields":{"published":"2018-01-05T20:26:25Z","referrer.host":[{"key":"toppuppies.co.uk","value":4413},{"key":"t.co","value":31},{"key":"www.my-daily-news-site-times.com","value":16},{"key":"m.example.com","value":8},{"key":"www-my-daily-news-site-times-com.cdn.ampproject.org","value":5}],"segment":{"path":"","slug":""},"title":"Trump Thinks Husband And Wife Should Do Their \u0026#8216;Own Thing,\u0026#8217; Alleges New Book"},"key":4720008,"metrics":{"bounce-rate":67.6,"hits":2549,"sessions":2170}},{"fields":{"published":"2018-01-05T17:02:04Z","referrer.host":[{"key":"toppuppies.co.uk","value":15461},{"key":"www.my-daily-news-site-times.com","value":109},{"key":"t.co","value":36},{"key":"apple.com","value":21},{"key":"cdn.example.com","value":17}],"segment":{"path":"","slug":""},"title":"Melania Trump\u0026#8217;s Racy \u0026#8216;New York Post\u0026#8217; Leaked Photos \u0026#8211; Everybody Assumed Donald Was Leaker, Melania Inconsolable"},"key":4719890,"metrics":{"bounce-rate":75.51,"hits":9127,"sessions":7245}},{"fields":{"published":"2018-01-05T13:59:21Z","referrer.host":[{"key":"toppuppies.co.uk","value":6227},{"key":"www.my-daily-news-site-times.com","value":45},{"key":"examplekittens.com","value":24},{"key":"apple.com","value":12},{"key":"www-my-daily-news-site-times-com.cdn.ampproject.org","value":11}],"segment":{"path":"","slug":""},"title":"Melania Trump Didn\u0026#8217;t Know Where Donald Was, Went Days Without Contact, Even When They Were Both In Trump Tower"},"key":4719626,"metrics":{"bounce-rate":77.18,"hits":3944,"sessions":2818}},{"fields":{"published":"2018-01-05T02:44:51Z","referrer.host":[{"key":"toppuppies.co.uk","value":3234},{"key":"plus.url.ing.example.com","value":534},{"key":"t.co","value":81},{"key":"www.my-daily-news-site-times.com","value":61},{"key":"examplekittens.com","value":45}],"segment":{"path":"","slug":""},"title":"Donald Trump Joked Sons \u0026#8216;Were In The Back Of The Room When God Handed Out Brains\u0026#8217;"},"key":4719039,"metrics":{"bounce-rate":82.1,"hits":2779,"sessions":2152}},{"fields":{"published":"2018-01-04T02:04:43Z","referrer.host":[{"key":"toppuppies.co.uk","value":11290},{"key":"www.my-daily-news-site-times.com","value":53},{"key":"www-my-daily-news-site-times-com.cdn.ampproject.org","value":30},{"key":"disq.us","value":18},{"key":"m.example.com","value":8}],"segment":{"path":"","slug":""},"title":"Book: top 10 best dog photos from every country"},"key":4716668,"metrics":{"bounce-rate":92.59,"hits":6262,"sessions":5553}}],"dimensions":["article.id"],"fields":{"referrer.host":[{"key":"toppuppies.co.uk","value":40625},{"key":"plus.url.ing.example.com","value":534},{"key":"www.my-daily-news-site-times.com","value":284},{"key":"t.co","value":148},{"key":"examplekittens.com","value":69},{"key":"www-my-daily-news-site-times-com.cdn.ampproject.org","value":46},{"key":"apple.com","value":33},{"key":"disq.us","value":18},{"key":"cdn.example.com","value":17},{"key":"m.example.com","value":16}]},"key":"2018-01-05T00:00:00.000Z","metrics":{"bounce-rate":80.35,"hits":24661,"sessions":19938}},{"details":[{"fields":{"published":"2018-01-04T21:42:56Z","referrer.host":[{"key":"toppuppies.co.uk","value":280},{"key":"apple.com","value":20},{"key":"t.co","value":9},{"key":"placekitten.com","value":6},{"key":"www.my-daily-news-site-times.com","value":5}],"segment":{"path":"news/","slug":"news"},"title":"BitCoin tops 1 million million million dollars today then crashes to 5 cents"},"key":4718638,"metrics":{"bounce-rate":71.6,"hits":192,"sessions":162}},{"fields":{"published":"2018-01-04T17:38:55Z","referrer.host":[{"key":"toppuppies.co.uk","value":342},{"key":"apple.com","value":70},{"key":"www.my-daily-news-site-times.com","value":8},{"key":"www.example.co.uk","value":7},{"key":"yahoo.com","value":6}],"segment":{"path":"news/","slug":"news"},"title":"By Definition Trump Uses A Misnomer For \u0026#8216;Misnomer\u0026#8217;"},"key":4718139,"metrics":{"bounce-rate":77.51,"hits":301,"sessions":258}},{"fields":{"published":"2018-01-04T16:20:48Z","referrer.host":[{"key":"toppuppies.co.uk","value":294},{"key":"www.my-daily-news-site-times.com","value":56},{"key":"www-my-daily-news-site-times-com.cdn.ampproject.org","value":32},{"key":"t.co","value":6},{"key":"apple.com","value":6}],"segment":{"path":"news/","slug":"news"},"title":"Books: They are worth reading, we swear."},"key":4717848,"metrics":{"bounce-rate":62.43,"hits":534,"sessions":362}},{"fields":{"published":"2018-01-04T03:02:37Z","referrer.host":[{"key":"toppuppies.co.uk","value":127},{"key":"apple.com","value":49},{"key":"www.my-daily-news-site-times.com","value":49},{"key":"yahoo.com","value":32},{"key":"www-my-daily-news-site-times-com.cdn.ampproject.org","value":25}],"segment":{"path":"","slug":""},"title":"Bitcoin: scam or scam?"},"key":4716889,"metrics":{"bounce-rate":69.85,"hits":497,"sessions":345}},{"fields":{"published":"2018-01-04T02:04:43Z","referrer.host":[{"key":"toppuppies.co.uk","value":14846},{"key":"www.my-daily-news-site-times.com","value":55},{"key":"www.reddit.com","value":40},{"key":"www-my-daily-news-site-times-com.cdn.ampproject.org","value":37},{"key":"apple.com","value":13}],"segment":{"path":"","slug":""},"title":"Book: top 10 best dog photos from every country"},"key":4716668,"metrics":{"bounce-rate":90.26,"hits":8308,"sessions":7377}}],"dimensions":["article.id"],"fields":{"referrer.host":[{"key":"toppuppies.co.uk","value":15889},{"key":"www.my-daily-news-site-times.com","value":173},{"key":"apple.com","value":158},{"key":"www-my-daily-news-site-times-com.cdn.ampproject.org","value":94},{"key":"www.reddit.com","value":40},{"key":"yahoo.com","value":38},{"key":"t.co","value":15},{"key":"www.example.co.uk","value":7},{"key":"placekitten.com","value":6}]},"key":"2018-01-04T00:00:00.000Z","metrics":{"bounce-rate":87.51,"hits":9832,"sessions":8504}}],"dimensions":["date","article.id"],"fields":{"identifier":"author-350","referrer.host":[{"key":"toppuppies.co.uk","value":117066},{"key":"examplekittens.com","value":4211},{"key":"www.my-daily-news-site-times.com","value":899},{"key":"yahoo.com","value":718},{"key":"apple.com","value":572},{"key":"plus.url.ing.example.com","value":534},{"key":"maybe.someone.used.bing.com","value":410},{"key":"t.co","value":223},{"key":"www-my-daily-news-site-times-com.cdn.ampproject.org","value":163},{"key":"news.ing.example.com","value":105},{"key":"duckduckgo.com","value":87},{"key":"www.reddit.com","value":45},{"key":"cdn.example.com","value":44},{"key":"r.search.aol.com","value":43},{"key":"placekitten.com","value":41},{"key":"m.example.com","value":37},{"key":"apple.com.au","value":28},{"key":"disq.us","value":18},{"key":"www.example.co.uk","value":7},{"key":"tatrenutek.si","value":6},{"key":"news.ing.example.com.au","value":6},{"key":"start.att.net","value":4},{"key":"www.letsrun.com","value":3}]},"key":350,"metrics":{"bounce-rate":84.46,"hits":74649,"sessions":59740}}],"dimensions":["author.id","date","article.id"],"enclosures":{"author-350":{"avatar":"https://secure.gravatar.com/avatar/7a18db45c9405ae51d93642e54fd02be?s=250\u0026d=mm\u0026r=g","id":350,"name":"Paula Mooney","nameClean":"paula-mooney","path":"author/paula/","slug":"paula","url":"https://www.my-daily-news-site-times.com/author/paula/"},"author-785":{"avatar":"https://secure.gravatar.com/avatar/2d6a237ef92afd4dd5eb18a059b10107?s=250\u0026d=mm\u0026r=g","id":785,"name":"Mic Florendo","nameClean":"mic-florendo","path":"author/michellefl/","slug":"michellefl","url":"https://www.my-daily-news-site-times.com/author/michellefl/"},"author-90":{"avatar":"https://secure.gravatar.com/avatar/296128ca60b6f95b1ab53ac044c46c3f?s=250\u0026d=mm\u0026r=g","id":90,"name":"Nathan Francis","nameClean":"nathan-francis","path":"author/nathan-francis/","slug":"nathan-francis","url":"https://www.my-daily-news-site-times.com/author/nathan-francis/"},"author-936":{"avatar":"https://secure.gravatar.com/avatar/7279b3662ceca772879caef009405f4d?s=250\u0026d=mm\u0026r=g","id":936,"name":"Simon Alvarez","nameClean":"simon-alvarez","path":"author/peterde/","slug":"peterde","url":"https://www.my-daily-news-site-times.com/author/peterde/"},"author-974":{"avatar":"https://secure.gravatar.com/avatar/4663c9853f526626ef9a0979c644cf18?s=250\u0026d=mm\u0026r=g","id":974,"name":"Roz Zurko","nameClean":"roz-zurko","path":"author/rozzu/","slug":"rozzu","url":"https://www.my-daily-news-site-times.com/author/rozzu/"}},"fields":{"referrer.host":[{"key":"toppuppies.co.uk","value":326929},{"key":"examplekittens.com","value":38962},{"key":"bestbarkernews.com","value":3281},{"key":"www.my-daily-news-site-times.com","value":2192},{"key":"apple.com","value":1967},{"key":"placekitten.com","value":1407},{"key":"yahoo.com","value":826},{"key":"maybe.someone.used.bing.com","value":622},{"key":"t.co","value":552},{"key":"plus.url.ing.example.com","value":550},{"key":"www-my-daily-news-site-times-com.cdn.ampproject.org","value":437},{"key":"news.ing.example.com","value":339},{"key":"m.example.com","value":212},{"key":"duckduckgo.com","value":139},{"key":"www.reddit.com","value":82},{"key":"r.search.aol.com","value":47},{"key":"cdn.example.com","value":44},{"key":"news.example.ca","value":34},{"key":"apple.com.au","value":32},{"key":"www.example.co.in","value":32},{"key":"www.linkedin.com","value":29},{"key":"www.example.co.uk","value":23},{"key":"disq.us","value":18},{"key":"www.topbuzz.com","value":18},{"key":"apple.news","value":18},{"key":"news.ing.example.com.au","value":15},{"key":"l.facebook.com","value":14},{"key":"route.overnewser.com","value":14},{"key":"t.umblr.com","value":13},{"key":"example.com","value":12},{"key":"amp-reddit-com.cdn.ampproject.org","value":11},{"key":"www.owler.com","value":10},{"key":"www.example.ca","value":8},{"key":"unboxholics.com","value":8},{"key":"www.exampleapis.com","value":6},{"key":"start.att.net","value":6},{"key":"tatrenutek.si","value":6},{"key":"a.example.com","value":4},{"key":"www.example.ae","value":4},{"key":"www.example.be","value":3},{"key":"www.letsrun.com","value":3},{"key":"frontpage.pch.com","value":2},{"key":"search.abclauncher.com","value":2},{"key":"www-earnthenecklace-com.cdn.ampproject.org","value":2},{"key":"ale.com.ng","value":2},{"key":"search.yahoo.com","value":2}]},"metrics":{"bounce-rate":85.27,"hits":225284,"sessions":183717}}
